LICENSE.txt
MANIFEST.in
README.md
requirements.txt
setup.py
tox.ini
django_timberjack.egg-info/PKG-INFO
django_timberjack.egg-info/SOURCES.txt
django_timberjack.egg-info/dependency_links.txt
django_timberjack.egg-info/not-zip-safe
django_timberjack.egg-info/requires.txt
django_timberjack.egg-info/top_level.txt
tests/__init__.py
tests/local_settings.py
tests/run_tests.py
tests/settings.py
tests/test_constants.py
tests/test_dereference.py
tests/test_django_forms_mixin.py
tests/test_documents.py
tests/test_fields.py
tests/test_rest_framework_mixin.py
tests/test_validators.py
tests/urls.py
tests/wsgi.py
tests/testapp/__init__.py
tests/testapp/admin.py
tests/testapp/apps.py
tests/testapp/models.py
tests/testapp/views.py
tests/testapp/migrations/__init__.py
timberjack/__init__.py
timberjack/admin.py
timberjack/apps.py
timberjack/dereference.py
timberjack/documents.py
timberjack/fields.py
timberjack/mixins.py
timberjack/validators.py
timberjack/compat/__init__.py
timberjack/compat/rest_framework/__init__.py
timberjack/compat/rest_framework/mixins.py
timberjack/templates/admin/timberjack/change_form.html
timberjack/templates/admin/timberjack/object_history.html