Metadata-Version: 1.1
Name: django-timberjack
Version: 0.0.4
Summary: MongoDB logging system
Home-page: https://github.com/rhblind/django-timberjack
Author: Rolf Håvard Blindheim
Author-email: rhblind@gmail.com
License: MIT License
Download-URL: https://github.com/rhblind/django-timberjack.git
Platform: UNKNOWN
Classifier: Operating System :: OS Independent
Classifier: Development Status :: 3 - Alpha
Classifier: Environment :: Web Environment
Classifier: Framework :: Django
Classifier: Intended Audience :: Developers
Classifier: License :: OSI Approved :: MIT License
Classifier: Programming Language :: Python :: 3.4
Classifier: Programming Language :: Python :: 3.5
Classifier: Topic :: Software Development :: Libraries :: Python Modules
